MANIFEST.in
README
setup.cfg
setup.py
TransAT_API.egg-info/PKG-INFO
TransAT_API.egg-info/SOURCES.txt
TransAT_API.egg-info/dependency_links.txt
TransAT_API.egg-info/requires.txt
TransAT_API.egg-info/top_level.txt
transat/__init__.py
transat/appbuilder.py
transat/loggers.py
transat/simulation.py
transat/apps/__init__.py
transat/apps/3D_pipe/__init__.py
transat/apps/3D_pipe/pipe.py
transat/apps/3D_pipe/pipe_postprocess.py
transat/apps/asymmetricalSplit/__init__.py
transat/apps/asymmetricalSplit/asymmetricalSplit.py
transat/apps/pipe/__init__.py
transat/apps/pipe/pipe.py
transat/apps/pipe/pipe_postprocess.py
transat/apps/pipe/test_pipe.py
transat/apps/severe_slug/__init__.py
transat/apps/severe_slug/loop.py
transat/apps/severe_slug/postprocess.py
transat/apps/severe_slug/run_loop.py
transat/apps/severe_slug/severe_slug.py
transat/apps/severe_slug/test_slug.py
transat/communicator/__init__.py
transat/communicator/communicator.py
transat/config/__init__.py
transat/config/ascomp_setup.py
transat/config/autoconf.py
transat/config/create_user_config.py
transat/config/globalconfig.py
transat/config/user_setup.py
transat/coupling/__init__.py
transat/coupling/coupling.py
transat/database/__init__.py
transat/database/database.py
transat/postproc/__init__.py
transat/postproc/open_paraview_for_project.py
transat/postproc/para_reader.py
transat/postproc/postprocessing.py
transat/postproc/test_outlet_results.py
transat/server/__init__.py
transat/server/client.py
transat/server/job.py
transat/server/server.py
transat/server/test_client.py
transat/server/test_server.py
transat/setup/__init__.py
transat/setup/bc.py
transat/setup/cad.py
transat/setup/ic.py
transat/setup/input.py
transat/setup/ist.py
transat/setup/mesh.py
transat/setup/setup.py
transat/setup/stt_helper_functions.py
transat/setup/test_bc.py
transat/setup/test_cad.py
transat/setup/test_input.py
transat/setup/test_mesh.py
transat/software/__init__.py
transat/software/installation.py
transat/software/software.py
transat/templates/asymmetricalSplit/initialconditions.cxx
transat/templates/asymmetricalSplit/three_pipes.stt
transat/templates/asymmetricalSplit/transat_mb.inp
