Metadata-Version: 1.0
Name: TransAT-API
Version: 0.5.3.3
Summary: API (driver) for TransAT, CFD simulation software
Home-page: http://www.ascomp.ch/
Author: Ascomp AG
Author-email: info@ascomp.ch
License: UNKNOWN
Platform: UNKNOWN
